ferrumpy/__init__.py
ferrumpy/bridge.py
ferrumpy/commands.py
ferrumpy/ferrumpy_core.abi3.so
ferrumpy/ffi_bridge.py
ferrumpy/path_resolver.py
ferrumpy/providers/__init__.py
ferrumpy/repl.py
ferrumpy/repl_ui.py
ferrumpy/serializer.py
ferrumpy/vendor/__init__.py
ferrumpy/vendor/prompt_toolkit/__init__.py
ferrumpy/vendor/prompt_toolkit/application/__init__.py
ferrumpy/vendor/prompt_toolkit/application/application.py
ferrumpy/vendor/prompt_toolkit/application/current.py
ferrumpy/vendor/prompt_toolkit/application/dummy.py
ferrumpy/vendor/prompt_toolkit/application/run_in_terminal.py
ferrumpy/vendor/prompt_toolkit/auto_suggest.py
ferrumpy/vendor/prompt_toolkit/buffer.py
ferrumpy/vendor/prompt_toolkit/cache.py
ferrumpy/vendor/prompt_toolkit/clipboard/__init__.py
ferrumpy/vendor/prompt_toolkit/clipboard/base.py
ferrumpy/vendor/prompt_toolkit/clipboard/in_memory.py
ferrumpy/vendor/prompt_toolkit/clipboard/pyperclip.py
ferrumpy/vendor/prompt_toolkit/completion/__init__.py
ferrumpy/vendor/prompt_toolkit/completion/base.py
ferrumpy/vendor/prompt_toolkit/completion/deduplicate.py
ferrumpy/vendor/prompt_toolkit/completion/filesystem.py
ferrumpy/vendor/prompt_toolkit/completion/fuzzy_completer.py
ferrumpy/vendor/prompt_toolkit/completion/nested.py
ferrumpy/vendor/prompt_toolkit/completion/word_completer.py
ferrumpy/vendor/prompt_toolkit/contrib/__init__.py
ferrumpy/vendor/prompt_toolkit/contrib/completers/__init__.py
ferrumpy/vendor/prompt_toolkit/contrib/completers/system.py
ferrumpy/vendor/prompt_toolkit/contrib/regular_languages/__init__.py
ferrumpy/vendor/prompt_toolkit/contrib/regular_languages/compiler.py
ferrumpy/vendor/prompt_toolkit/contrib/regular_languages/completion.py
ferrumpy/vendor/prompt_toolkit/contrib/regular_languages/lexer.py
ferrumpy/vendor/prompt_toolkit/contrib/regular_languages/regex_parser.py
ferrumpy/vendor/prompt_toolkit/contrib/regular_languages/validation.py
ferrumpy/vendor/prompt_toolkit/contrib/ssh/__init__.py
ferrumpy-0.1.5.dist-info/METADATA
ferrumpy-0.1.5.dist-info/WHEEL
ferrumpy-0.1.5.dist-info/RECORD
