Metadata-Version: 2.4
Name: ferrumpy
Version: 0.1.5
Summary: Rust debugger enhancements for LLDB
Requires-Python: >=3.9
